nodevectors2/__init__.py
nodevectors2/embedders.py
nodevectors2/ggvec.py
nodevectors2/glove.py
nodevectors2/grarep.py
nodevectors2/node2vec.py
nodevectors2/prone.py
nodevectors2/evaluation/__init__.py
nodevectors2/evaluation/graph_eval.py
nodevectors2/evaluation/link_pred.py
nodevectors2-0.1.23.dist-info/LICENSE.txt
nodevectors2-0.1.23.dist-info/METADATA
nodevectors2-0.1.23.dist-info/WHEEL
nodevectors2-0.1.23.dist-info/top_level.txt
nodevectors2-0.1.23.dist-info/RECORD
