Metadata-Version: 2.1
Name: nodevectors2
Version: 0.1.23
Summary: Fast network node embeddings
Home-page: https://github.com/VHRanger/nodevectors/
Author: Matt Ranger
License: MIT
Keywords: graph,network,embedding,node2vec
License-File: LICENSE.txt
Requires-Dist: csrgraph2
Requires-Dist: gensim (==3.6.0)
Requires-Dist: networkx
Requires-Dist: numba
Requires-Dist: numpy
Requires-Dist: pandas (>=1.0)
Requires-Dist: scipy
Requires-Dist: scikit-learn
